pytest_testrail_results/__init__.py
pytest_testrail_results/conftest.py
pytest_testrail_results/plugin.py
pytest_testrail_results/testrail_api.py
pytest_testrail_results-1.0.2.dist-info/LICENSE
pytest_testrail_results-1.0.2.dist-info/METADATA
pytest_testrail_results-1.0.2.dist-info/WHEEL
pytest_testrail_results-1.0.2.dist-info/entry_points.txt
pytest_testrail_results-1.0.2.dist-info/top_level.txt
pytest_testrail_results-1.0.2.dist-info/RECORD
