Metadata-Version: 2.1
Name: pytest_testrail_results
Version: 1.0.2
Summary: A pytest plugin to upload results to TestRail.
Author: Oleg_Miroshnychenko
Author-email: miroshnychenko@dnt-lab.com
Classifier: Programming Language :: Python :: 3.7
Classifier: Programming Language :: Python :: 3.8
Classifier: Programming Language :: Python :: 3.9
Classifier: Programming Language :: Python :: 3.10
Classifier: Programming Language :: Python :: 3.11
Classifier: License :: OSI Approved :: MIT License
Classifier: Operating System :: OS Independent
License-File: LICENSE
Requires-Dist: pytest >=7.2.0
Requires-Dist: requests >=2.30.0
